YkPywebview/__init__.py
YkPywebview/core.py
YkPywebview/test.py
YkPywebview/version.py
ykpywebview-25.7.43.dist-info/METADATA
ykpywebview-25.7.43.dist-info/WHEEL
ykpywebview-25.7.43.dist-info/top_level.txt
ykpywebview-25.7.43.dist-info/RECORD
