Metadata-Version: 2.4
Name: YkPywebview
Version: 25.7.43
Summary: A wrapper library for pywebview with enhanced features
Home-page: https://gitee.com/yangke02/yk-pywebview
Author: Yang Ke
Author-email: 540673597@qq.com
License: MIT
Classifier: Programming Language :: Python :: 3
Classifier: Operating System :: OS Independent
Requires-Python: >=3.10
Requires-Dist: pywebview>=3.0
Dynamic: author
Dynamic: author-email
Dynamic: classifier
Dynamic: description
Dynamic: description-content-type
Dynamic: home-page
Dynamic: license
Dynamic: requires-dist
Dynamic: requires-python
Dynamic: summary
